{
  "generado": "2026-07-21",
  "n_resueltos": 272,
  "estado": "activo",
  "global": {
    "n": 272,
    "wins": 161,
    "losses": 108,
    "pushes": 3,
    "win_pct": 59.9,
    "roi": 2.6
  },
  "por_deporte": {
    "FIFA World Cup 2026": {
      "n": 59,
      "wins": 45,
      "losses": 13,
      "pushes": 1,
      "win_pct": 77.6,
      "roi": 25.2
    },
    "MLB": {
      "n": 213,
      "wins": 116,
      "losses": 95,
      "pushes": 2,
      "win_pct": 55.0,
      "roi": -4.0
    }
  },
  "por_tipo": {
    "Moneyline": {
      "n": 236,
      "wins": 141,
      "losses": 93,
      "pushes": 2,
      "win_pct": 60.3,
      "roi": 2.4
    },
    "Spread": {
      "n": 8,
      "wins": 1,
      "losses": 7,
      "pushes": 0,
      "win_pct": 12.5,
      "roi": -81.0
    },
    "Total": {
      "n": 28,
      "wins": 19,
      "losses": 8,
      "pushes": 1,
      "win_pct": 70.4,
      "roi": 31.0
    }
  },
  "por_estrellas": {
    "2": {
      "n": 4,
      "win_pct": 50.0
    },
    "3": {
      "n": 55,
      "win_pct": 56.4
    },
    "4": {
      "n": 25,
      "win_pct": 48.0
    },
    "5": {
      "n": 1,
      "win_pct": 0.0
    }
  },
  "calibracion": [
    {
      "rango": "≤52",
      "n": 8,
      "prometido": 49.6,
      "real": 50.0,
      "sesgo": -0.4
    },
    {
      "rango": "52-60",
      "n": 42,
      "prometido": 55.2,
      "real": 54.8,
      "sesgo": 0.4
    },
    {
      "rango": "60-68",
      "n": 27,
      "prometido": 63.5,
      "real": 55.6,
      "sesgo": 7.9
    },
    {
      "rango": "68+",
      "n": 8,
      "prometido": 71.8,
      "real": 37.5,
      "sesgo": 34.3
    }
  ],
  "lecciones": "APRENDIZAJE DE PICKS PASADOS (úsalo para calibrar tu criterio):\n- Global: 161-108 (59.9% acierto), ROI +2.6%/u en 272 picks.\n- Mejor deporte: FIFA World Cup 2026 (77.6%, ROI +25.2%).\n- Peor deporte: MLB (55.0%, ROI -4.0%) — sé más selectivo ahí.\n- Tipo flojo: Spread (12.5%, ROI -81.0%) — evita salvo ventaja clara.\n- Calibración: prometiste 58.9% promedio pero ganó 52.9% — sobreestimas ~6.0 pts, baja tus probabilidades.\n- 5★ ganan 0.0% vs 3★ 56.4% — tus 5★ NO ganan más; modera la confianza."
}