{
  "fecha": "2026-07-09",
  "fecha_display": "Jueves 9 de Julio 2026",
  "generado_a": "automatico-github-actions",
  "nota_lineas": "Cuota de consenso (mediana entre casas). Probabilidad ANCLADA al mercado sharp (Pinnacle) — la IA no inventa favoritos. La cuota mínima es el precio que tu casa (PlayDoIt/Winpot) debe superar. 8 picks con EV+. Horario CDT CDMX.",
  "bankroll": {
    "exposicion_total": "2.1u",
    "max_por_juego": "0.3u",
    "nota": "Kelly 1/4"
  },
  "picks": [
    {
      "liga": "MLB",
      "matchup": "Athletics @ Detroit Tigers",
      "hora": "5:41 PM CDT (CDMX)",
      "pick": "Detroit Tigers ML",
      "tipo": "Moneyline",
      "cuota_bet365": 1.78,
      "prob_implicita": 56.2,
      "prob_propia": 59.8,
      "ev_pct": 6.4,
      "prob_acierto": 60,
      "estrellas": 4,
      "stake": "0.25u",
      "razonamiento": "Troy Melton tiene ERA de 1.82 con récord 5-1, el mejor abridor disponible hoy en el contexto. Detroit es local (25-21 en casa) frente a Athletics (22-23 visitante). Jeffrey Springs está con ERA 6.08 y récord 3-9, lo que representa una ventaja pitching masiva. El mercado asigna ~56% a Detroit, pero con esta disparidad de abridores estimo ~60% real. Edge claro y defendible.",
      "sport_key": "baseball_mlb",
      "cuota_verificada": true,
      "prob_ia_cruda": 60.0,
      "prob_justa": 54.8,
      "fair_source": "pinnacle",
      "cuota_minima": 1.67
    },
    {
      "liga": "MLB",
      "matchup": "Milwaukee Brewers @ St. Louis Cardinals",
      "hora": "6:46 PM CDT (CDMX)",
      "pick": "Milwaukee Brewers ML",
      "tipo": "Moneyline",
      "cuota_bet365": 1.77,
      "prob_implicita": 56.5,
      "prob_propia": 60.0,
      "ev_pct": 6.2,
      "prob_acierto": 60,
      "estrellas": 4,
      "stake": "0.25u",
      "razonamiento": "Brewers son el mejor equipo del contexto MLB hoy (58-34, mejor récord), con 29-16 de visitante. Kyle Harrison lleva récord 8-2 con ERA 3.01. Cardinals están en 48-43 con record local 24-24 y su abridor McGreevy tiene ERA 3.01 pero récord 4-7. La diferencia en calidad de roster (58-34 vs 48-43) justifica estimar ~60% para Milwaukee. El mercado solo les da ~56%.",
      "sport_key": "baseball_mlb",
      "cuota_verificada": true,
      "prob_ia_cruda": 60.0,
      "prob_justa": 55.3,
      "fair_source": "pinnacle",
      "cuota_minima": 1.67
    },
    {
      "liga": "MLB",
      "matchup": "Tampa Bay Rays vs New York Yankees",
      "hora": "12:10 PM CDT (CDMX)",
      "pick": "Tampa Bay Rays ML",
      "tipo": "Moneyline",
      "cuota_bet365": 1.69,
      "prob_implicita": 59.2,
      "prob_propia": 62.0,
      "ev_pct": 4.8,
      "prob_acierto": 62,
      "estrellas": 3,
      "stake": "0.2u",
      "razonamiento": "Rays son el segundo mejor equipo del contexto (54-36) y locales con récord impresionante 33-13 en casa. Shane McClanahan lleva 8-5 con ERA 2.83. Yankees tienen abridor TBD (desconocido) lo que añade incertidumbre para New York. Rays con ERA de abridor mucho más baja y ventaja local sólida justifican ~62% real vs 59.2% implícita del mercado.",
      "sport_key": "baseball_mlb",
      "cuota_verificada": false,
      "prob_ia_cruda": 62.0,
      "prob_justa": null,
      "fair_source": null,
      "cuota_minima": 1.61
    },
    {
      "liga": "MLB",
      "matchup": "Philadelphia Phillies @ Cincinnati Reds",
      "hora": "6:11 PM CDT (CDMX)",
      "pick": "Cincinnati Reds ML",
      "tipo": "Moneyline",
      "cuota_bet365": 2.33,
      "prob_implicita": 42.9,
      "prob_propia": 46.8,
      "ev_pct": 9.0,
      "prob_acierto": 47,
      "estrellas": 3,
      "stake": "0.2u",
      "razonamiento": "Chase Burns es el pitcher más dominante del contexto hoy: 11-1 con ERA 2.54. Phillies mandan al montículo a Alan Rangel con récord 0-2 y ERA 4.19. Aunque Phillies tienen mejor récord general (51-42 vs 42-49), la ventaja de pitching para Cincinnati es enorme. El mercado paga 2.33 a Reds, equivalente a solo ~43% implícita — con Burns en el montículo, estimo ~47% real. EV positivo a buen precio.",
      "sport_key": "baseball_mlb",
      "cuota_verificada": true,
      "prob_ia_cruda": 47.0,
      "prob_justa": 41.8,
      "fair_source": "pinnacle",
      "cuota_minima": 2.14
    },
    {
      "liga": "MLB",
      "matchup": "Boston Red Sox @ Chicago White Sox",
      "hora": "1:11 PM CDT (CDMX)",
      "pick": "Chicago White Sox ML",
      "tipo": "Moneyline",
      "cuota_bet365": 1.99,
      "prob_implicita": 50.3,
      "prob_propia": 54.1,
      "ev_pct": 7.7,
      "prob_acierto": 55,
      "estrellas": 3,
      "stake": "0.2u",
      "razonamiento": "White Sox son locales con récord impresionante 28-16 en casa (mejor récord local del contexto junto a Rays). Davis Martin tiene 9-4 con ERA 3.41. Red Sox mandan a Jake Bennett (4-3, ERA 2.64, bueno pero no superior). El récord local de Chicago (28-16) es el diferencial clave — el mercado los trata casi como partido parejo (51.8% implícita) cuando su ventaja de casa es real. Estimo ~55%.",
      "sport_key": "baseball_mlb",
      "cuota_verificada": true,
      "prob_ia_cruda": 55.0,
      "prob_justa": 49.1,
      "fair_source": "pinnacle",
      "cuota_minima": 1.85
    },
    {
      "liga": "Tennis WTA",
      "matchup": "Coco Gauff @ Karolina Muchova",
      "hora": "7:30 AM CDT (CDMX)",
      "pick": "Karolina Muchova ML",
      "tipo": "Moneyline",
      "cuota_bet365": 1.85,
      "prob_implicita": 54.1,
      "prob_propia": 55.0,
      "ev_pct": 1.8,
      "prob_acierto": 55,
      "estrellas": 2,
      "stake": "0.15u",
      "razonamiento": "Partido casi parejo (1.90 vs 2.03). Muchova es la favorita ligera del mercado. La cuota de 1.90 para Muchova ofrece valor marginal si se estima ~55% real para ella. Partido muy abierto — stake conservador dada la incertidumbre en tenis y la falta de estadísticas de forma reciente en el contexto.",
      "sport_key": "tennis_wta_wimbledon",
      "cuota_verificada": true,
      "prob_ia_cruda": 55.0,
      "prob_justa": 51.9,
      "fair_source": "pinnacle",
      "cuota_minima": 1.82
    },
    {
      "liga": "MLB",
      "matchup": "San Francisco Giants vs Colorado Rockies",
      "hora": "8:46 PM CDT (CDMX)",
      "pick": "San Francisco Giants ML",
      "tipo": "Moneyline",
      "cuota_bet365": 1.71,
      "prob_implicita": 58.5,
      "prob_propia": 61.0,
      "ev_pct": 4.3,
      "prob_acierto": 61,
      "estrellas": 2,
      "stake": "0.15u",
      "razonamiento": "Colorado Rockies tienen abridor TBD (incertidumbre negativa para ellos). Giants son favoritos locales a 1.71. Rockies son históricamente el peor equipo de viaje en béisbol por la diferencia de altitud. Con abridor desconocido de Colorado y la ventaja local de SF, estimo ~61% para Giants. Edge pequeño pero cuota razonable. Nota: Casa de apuesta es Betway (única disponible para este partido según contexto).",
      "sport_key": "baseball_mlb",
      "cuota_verificada": false,
      "prob_ia_cruda": 61.0,
      "prob_justa": null,
      "fair_source": null,
      "cuota_minima": 1.64
    },
    {
      "liga": "MLB",
      "matchup": "Chicago Cubs @ Baltimore Orioles",
      "hora": "12:36 PM CDT (CDMX)",
      "pick": "Chicago Cubs ML",
      "tipo": "Moneyline",
      "cuota_bet365": 2.1,
      "prob_implicita": 47.6,
      "prob_propia": 50.8,
      "ev_pct": 6.7,
      "prob_acierto": 51,
      "estrellas": 2,
      "stake": "0.15u",
      "razonamiento": "Cubs tienen mejor récord (52-40 vs 42-51 de Orioles) y son visitantes competitivos (25-21 fuera). Baltimore es el equipo local con peor récord del día entre los favoritos (42-51, local 24-25). El abridor de Baltimore Dean Kremer tiene récord 1-2 con ERA 4.09 vs Colin Rea de Chicago (7-5, ERA 4.75 — comparable). La calidad diferencial del roster (52-40 vs 42-51) justifica que Cubs sean el pick de valor aquí a 2.13.",
      "sport_key": "baseball_mlb",
      "cuota_verificada": true,
      "prob_ia_cruda": 51.0,
      "prob_justa": 45.8,
      "fair_source": "pinnacle",
      "cuota_minima": 1.97
    }
  ],
  "no_apostar": [
    {
      "matchup": "Atlanta Braves @ Pittsburgh Pirates",
      "liga": "MLB",
      "razon": "Los abridores en el contexto no coinciden con los listados (contexto de cuotas muestra Holmes/Jones, picks muestran Elder/Keller). Incertidumbre de pitcher crea riesgo de línea incorrecta. Mercado casi parejo (1.87/2.06) sin ventaja clara identificable."
    },
    {
      "matchup": "Kansas City Royals @ New York Mets",
      "liga": "MLB",
      "razon": "Ambos equipos tienen récords perdedores (38-55 y 39-54). El abridor del contexto de cuotas (Steven Cruz 5.22 ERA) difiere del listado de partidos (Michael Wacha). Incertidumbre de datos. Partido sin ventaja clara."
    },
    {
      "matchup": "Cleveland Guardians @ Minnesota Twins",
      "liga": "MLB",
      "razon": "Ambos equipos con récords casi idénticos (~47-46 y 46-47) y abridores mediocres (ERA 4.55 vs 5.00). Sin ventaja estadística clara que justifique apuesta. Mercado refleja correctamente el partido equilibrado."
    },
    {
      "matchup": "Seattle Mariners @ Miami Marlins",
      "liga": "MLB",
      "razon": "Mariners tienen record visitante pobre (20-26) pese a ser favoritos del mercado. Marlins locales sólidos (30-17 en casa) pero el mercado ya descuenta esto pagando 2.29. Sin edge claro suficiente para justificar apuesta."
    },
    {
      "matchup": "Arizona Diamondbacks @ San Diego Padres",
      "liga": "MLB",
      "razon": "Jose Cabrera (0-2, 5.60 ERA) para Arizona es débil, pero el mercado ya castiga a Diamondbacks con 2.10. Sin ventaja adicional identificable sobre lo que el mercado ya ha priceado. Pass."
    },
    {
      "matchup": "Colorado Rockies @ San Francisco Giants",
      "liga": "MLB",
      "razon": "Solo disponible en Betway (no 1xBet). Cuota limitada sin datos estadísticos completos de abridores para Giants (TBD). Confianza reducida por ausencia de pitcher confirmado del local."
    },
    {
      "matchup": "Linda Noskova @ Marta Kostyuk",
      "liga": "Tennis WTA",
      "razon": "Sin estadísticas de forma reciente en el contexto para fundamentar edge real. Mercado paga 1.78 a Kostyuk (favorita clara) sin datos que permitan estimar probabilidad propia con confianza. Pass."
    },
    {
      "matchup": "Athletics @ Detroit Tigers",
      "liga": "MLB",
      "razon": "Sin valor: EV -1.7%. Anclada al mercado, la prob real (52.0%) no supera lo que implica la cuota (52.9%)."
    },
    {
      "matchup": "Los Angeles Angels @ Texas Rangers",
      "liga": "MLB",
      "razon": "Sin valor: EV -1.5%. Anclada al mercado, la prob real (50.0%) no supera lo que implica la cuota (50.8%)."
    }
  ],
  "parlay_sugerido": {
    "patas": [
      "Detroit Tigers ML (1.78)",
      "Milwaukee Brewers ML (1.78)",
      "Tampa Bay Rays ML (1.69)"
    ],
    "cuota_total": 5.06,
    "ev_pct": 9.2,
    "stake": "0.15u",
    "nota": "Las tres patas comparten el mismo perfil: equipo de mejor récord general con abridor de ERA baja frente a rival con abridor con ERA alta o desconocido. Correlación positiva por selección de equipos con ventaja pitching clara el mismo día. Melton (ERA 1.82), Harrison (ERA 3.01/récord 8-2) y McClanahan (ERA 2.83) son los mejores abridores confirmados de sus respectivos juegos."
  },
  "resumen_ejecutivo": [
    {
      "pick": "Detroit Tigers ML",
      "tipo": "Moneyline",
      "liga": "MLB",
      "cuota": 1.78,
      "ev_pct": 6.8,
      "stake": "0.25u",
      "estrellas": 4
    },
    {
      "pick": "Milwaukee Brewers ML",
      "tipo": "Moneyline",
      "liga": "MLB",
      "cuota": 1.78,
      "ev_pct": 6.8,
      "stake": "0.25u",
      "estrellas": 4
    },
    {
      "pick": "Tampa Bay Rays ML",
      "tipo": "Moneyline",
      "liga": "MLB",
      "cuota": 1.69,
      "ev_pct": 4.8,
      "stake": "0.2u",
      "estrellas": 3
    },
    {
      "pick": "Cincinnati Reds ML",
      "tipo": "Moneyline",
      "liga": "MLB",
      "cuota": 2.33,
      "ev_pct": 9.6,
      "stake": "0.2u",
      "estrellas": 3
    },
    {
      "pick": "Under 8.5 (Athletics @ Detroit)",
      "tipo": "Total",
      "liga": "MLB",
      "cuota": 2.12,
      "ev_pct": 10.2,
      "stake": "0.2u",
      "estrellas": 3
    },
    {
      "pick": "Chicago White Sox ML",
      "tipo": "Moneyline",
      "liga": "MLB",
      "cuota": 1.93,
      "ev_pct": 6.2,
      "stake": "0.2u",
      "estrellas": 3
    },
    {
      "pick": "Under 6.5 (LAA @ TEX)",
      "tipo": "Total",
      "liga": "MLB",
      "cuota": 2.21,
      "ev_pct": 10.5,
      "stake": "0.2u",
      "estrellas": 3
    },
    {
      "pick": "Karolina Muchova ML",
      "tipo": "Moneyline",
      "liga": "Tennis WTA",
      "cuota": 1.9,
      "ev_pct": 4.5,
      "stake": "0.15u",
      "estrellas": 2
    },
    {
      "pick": "San Francisco Giants ML",
      "tipo": "Moneyline",
      "liga": "MLB",
      "cuota": 1.71,
      "ev_pct": 4.3,
      "stake": "0.15u",
      "estrellas": 2
    },
    {
      "pick": "Chicago Cubs ML",
      "tipo": "Moneyline",
      "liga": "MLB",
      "cuota": 2.13,
      "ev_pct": 8.6,
      "stake": "0.15u",
      "estrellas": 2
    }
  ]
}